pyrolite/__init__.py
pyrolite/_version.py
pyrolite/comp/__init__.py
pyrolite/comp/aggregate.py
pyrolite/comp/codata.py
pyrolite/comp/impute.py
pyrolite/data/Aitchison/__init__.py
pyrolite/data/Aitchison/boxite.csv
pyrolite/data/Aitchison/coxite.csv
pyrolite/data/Aitchison/hongite.csv
pyrolite/data/Aitchison/kongite.csv
pyrolite/data/_config/pyrolite.mplstyle
pyrolite/data/geochem/geochemdb.json
pyrolite/data/geochem/refcomp_template.csv
pyrolite/data/geochem/refdb.json
pyrolite/data/geochem/refcomp/ARS_Condie1993.csv
pyrolite/data/geochem/refcomp/BCC_McLennan2001.csv
pyrolite/data/geochem/refcomp/BCC_RudnickGao2003.csv
pyrolite/data/geochem/refcomp/BCC_RudnickGao2014.csv
pyrolite/data/geochem/refcomp/CH_McDonoughSun1995.csv
pyrolite/data/geochem/refcomp/CH_PalmeONeill2014.csv
pyrolite/data/geochem/refcomp/CH_REE_ONeill2016.csv
pyrolite/data/geochem/refcomp/CH_SunMcDonough1989.csv
pyrolite/data/geochem/refcomp/DDMM_WorkmanHart2005.csv
pyrolite/data/geochem/refcomp/DMM_WorkmanHart2005.csv
pyrolite/data/geochem/refcomp/DMORB_Gale2013.csv
pyrolite/data/geochem/refcomp/DM_SaltersStrake2004.csv
pyrolite/data/geochem/refcomp/EDMM_WorkmanHart2005.csv
pyrolite/data/geochem/refcomp/EMORB_Gale2013.csv
pyrolite/data/geochem/refcomp/EMORB_SunMcDonough1989.csv
pyrolite/data/geochem/refcomp/EUS_Bau2018.csv
pyrolite/data/geochem/refcomp/GLOSS2_Plank2014.csv
pyrolite/data/geochem/refcomp/GLOSS_Plank2014.csv
pyrolite/data/geochem/refcomp/LCC_McLennan2001.csv
pyrolite/data/geochem/refcomp/LCC_RudnickGao2003.csv
pyrolite/data/geochem/refcomp/LCC_RudnickGao2014.csv
pyrolite/data/geochem/refcomp/MCC_RudnickGao2014.csv
pyrolite/data/geochem/refcomp/MORB_Gale2013.csv
pyrolite/data/geochem/refcomp/MUQ_Kamber2005.csv
pyrolite/data/geochem/refcomp/NASC_Gromet1984.csv
pyrolite/data/geochem/refcomp/NMORB_Gale2013.csv
pyrolite/data/geochem/refcomp/NMORB_SunMcDonough1989.csv
pyrolite/data/geochem/refcomp/OIB_SunMcDonough1989.csv
pyrolite/data/geochem/refcomp/PAAS_Pourmand2012.csv
pyrolite-0.3.6.dist-info/LICENSE
pyrolite-0.3.6.dist-info/METADATA
pyrolite-0.3.6.dist-info/WHEEL
pyrolite-0.3.6.dist-info/top_level.txt
pyrolite-0.3.6.dist-info/RECORD
