Metadata-Version: 2.1
Name: pyrolite
Version: 0.3.6
Summary: Tools for geochemical data analysis.
Author-email: Morgan Williams <morgan.williams@csiro.au>
License: CSIRO Open Source Software Licence Agreement (Variation of the BSD/MIT License)
Project-URL: Issues, https://github.com/morganjwilliams/pyrolite/issues
Project-URL: Documentation, https://pyrolite.readthedocs.io/
Project-URL: Repository, https://github.com/morganjwilliams/pyrolite
Project-URL: Changelog, https://github.com/me/spam/blob/master/CHANGELOG.md
Keywords: geochemistry,compositional data,visualisation,petrology
Classifier: Development Status :: 4 - Beta
Classifier: Intended Audience :: Science/Research
Classifier: Intended Audience :: Education
Classifier: Natural Language :: English
Classifier: Programming Language :: Python :: 3 :: Only
Classifier: Programming Language :: Python :: 3.8
Classifier: Programming Language :: Python :: 3.9
Classifier: Programming Language :: Python :: 3.10
Classifier: Programming Language :: Python :: 3.11
Classifier: Programming Language :: Python :: 3.12
Classifier: Framework :: Matplotlib
Classifier: Topic :: Scientific/Engineering
Classifier: Topic :: Software Development :: Libraries :: Python Modules
Requires-Python: >=3.8
License-File: LICENSE
Requires-Dist: numpy
Requires-Dist: numpydoc
Requires-Dist: tinydb>4.1
Requires-Dist: periodictable
Requires-Dist: matplotlib<3.9
Requires-Dist: mpltern>=0.4.0
Requires-Dist: scipy>=1.2
Requires-Dist: sympy>=1.7
Requires-Dist: pandas>=1.0
Requires-Dist: requests
Provides-Extra: db
Requires-Dist: pyodbc; extra == "db"
Requires-Dist: psycopg2; extra == "db"
Provides-Extra: dev
Requires-Dist: pytest; extra == "dev"
Requires-Dist: versioneer; extra == "dev"
Requires-Dist: black; extra == "dev"
Requires-Dist: isort; extra == "dev"
Requires-Dist: twine; extra == "dev"
Requires-Dist: pyrolite[docs,skl,test]; extra == "dev"
Requires-Dist: build; extra == "dev"
Provides-Extra: docs
Requires-Dist: sphinx-rtd-theme; extra == "docs"
Requires-Dist: docutils<0.17; extra == "docs"
Requires-Dist: sphinx>=4; extra == "docs"
Requires-Dist: sphinx-autodoc-annotation; extra == "docs"
Requires-Dist: sphinx-gallery>=0.6.0; extra == "docs"
Requires-Dist: recommonmark; extra == "docs"
Provides-Extra: excel
Requires-Dist: xlrd; extra == "excel"
Requires-Dist: openpyxl; extra == "excel"
Provides-Extra: skl
Requires-Dist: scikit-learn; extra == "skl"
Requires-Dist: joblib; extra == "skl"
Provides-Extra: spatial
Requires-Dist: owslib; extra == "spatial"
Requires-Dist: geojson; extra == "spatial"
Requires-Dist: psutil; extra == "spatial"
Provides-Extra: stats
Requires-Dist: statsmodels; extra == "stats"
Requires-Dist: scikit-learn; extra == "stats"
Provides-Extra: test
Requires-Dist: pytest; extra == "test"
Requires-Dist: pytest-runner; extra == "test"
Requires-Dist: pytest-cov; extra == "test"
Requires-Dist: coverage; extra == "test"
Requires-Dist: coveralls; extra == "test"
